poouli/__init__.py
poouli/load_config.py
poouli/main.py
poouli-0.3.0.dist-info/licenses/LICENSE
poouli-0.3.0.dist-info/WHEEL
poouli-0.3.0.dist-info/entry_points.txt
poouli-0.3.0.dist-info/METADATA
poouli-0.3.0.dist-info/RECORD
