Metadata-Version: 2.4
Name: poouli
Version: 0.3.0
Summary: Syncronize local files with MediaWiki
Keywords: Experimental Publishing,Markdown,MediaWiki,Notes,Pandoc,Wiki,XPUB,Zettelkasten
Author: Tommi
Author-email: Tommi <surfing@tommi.space>
License-Expression: EUPL-1.2
License-File: LICENSE
Classifier: Development Status :: 3 - Alpha
Classifier: Environment :: Console
Classifier: Natural Language :: English
Classifier: Operating System :: OS Independent
Classifier: Programming Language :: Python :: 3
Classifier: Programming Language :: Python :: 3.13
Classifier: Topic :: Documentation
Classifier: Topic :: Internet
Classifier: Topic :: Text Processing
Classifier: Topic :: Text Processing :: Markup :: Markdown
Classifier: Topic :: Utilities
Requires-Dist: pypandoc-binary>=1.15
Requires-Dist: python-frontmatter>=1.1.0
Requires-Dist: pywikibot>=10.6.0
Requires-Dist: pyyaml>=6.0.3
Requires-Dist: setuptools>=80.9.0
Requires-Python: >=3.12
Project-URL: Changelog, https://codeberg.org/tommi/poouli/commits/branch/main
Project-URL: Issues, https://codeberg.org/tommi/poouli/issues
Project-URL: Repository, https://codeberg.org/tommi/poouli
